{"type":"controller","name":"Department","module":"department","description":"postDepartment","basePath":"api","actions":[{"actionName":"postDepartment","path":"department","method":"POST","requestBody":{"content":{"application/json":{"schema":{"type":"Department","name":"Department","isRequired":true,"objectType":"dto","module":"shared"}}}},"responses":{"201":{"name":"OK","content":{"application/json":{"schema":{"type":"string","name":"data","collectionType":"none"}}}}}},{"actionName":"getDepartments","path":"departments","method":"GET","responses":{"200":{"description":"List of Departments","content":{"application/json":{"schema":{"type":"DepartmentDTO","objectType":"dto","name":"data","collectionType":"none","module":"shared"}}}}}},{"actionName":"getDepartmentById","path":"departments/{id}","method":"GET","responses":{"200":{"description":"Department Data","content":{"application/json":{"schema":{"type":"DepartmentDTO","objectType":"dto","name":"data","collectionType":"none","module":"shared"}}}}},"pathVariables":[{"type":"integer","name":"id","description":"ID of the Department","isRequired":true}]},{"actionName":"updateDepartment","path":"departments/{id}","method":"PUT","requestBody":{"content":{"application/json":{"schema":{"type":"DepartmentDTO","name":"Department","description":"Department Data","objectType":"dto","module":"shared"}}}},"responses":{"200":{"description":"Updated Department","content":{"application/json":{"schema":{"type":"DepartmentDTO","objectType":"dto","name":"data","collectionType":"none","module":"shared"}}}}},"pathVariables":[{"type":"integer","name":"id","description":"ID of the Department","isRequired":true}]},{"actionName":"deleteDepartment","path":"departments/{id}","method":"DELETE","responses":{"204":{"content":{"":{"schema":{"type":"string","name":"data","collectionType":"none"}}}}},"pathVariables":[{"type":"integer","name":"id","description":"ID of the Department","isRequired":true}]}],"id":"u2pwso5tbi-CONTROLLER-CONTROLLER-CONTROLLER-CONTROLLER-CONTROLLER"}